{
  "kind": "collectionType",
  "collectionName": "big_zalads",
  "info": {
    "singularName": "big-zalad",
    "pluralName": "big-zalads",
    "displayName": "Big Zalad"
  },
  "options": {
    "draftAndPublish": true
  },
  "pluginOptions": {},
  "attributes": {
    "Title": {
      "type": "string",
      "required": true
    },
    "Price": {
      "type": "string",
      "required": true
    },
    "Calories": {
      "type": "string",
      "required": true
    },
    "Description": {
      "type": "text",
      "required": true
    },
    "slug": {
      "type": "uid",
      "targetField": "Title"
    },
    "Image": {
      "allowedTypes": [
        "images",
        "files",
        "videos",
        "audios"
      ],
      "type": "media",
      "multiple": false
    }
  }
}
